{
  "timestamp": "2025-12-12T02:05:06.115512-03:00",
  "url": "https://www.godo.sr/nl/wisselkoersnoteringen/",
  "method": "GET",
  "headers": {
    "user-agent": "Mozilla/5.0 (Windows NT 10.0; Win64; x64) AppleWebKit/537.36 (KHTML, like Gecko) Chrome/124.0.0.0 Safari/537.36",
    "accept": "*/*",
    "accept-language": "nl-NL,nl;q=0.9,en;q=0.8",
    "connection": "keep-alive"
  },
  "body": "None",
  "ip_local": "127.0.1.1",
  "traceroute": "traceroute to uwxiy.x.incapdns.net (199.83.129.128), 15 hops max\n  1   140.204.226.197  0.258ms  0.139ms  0.111ms \n  2   128.241.7.147  1.112ms  1.078ms  1.105ms \n  3   128.241.7.146  8.784ms  8.602ms  8.689ms \n  4   *  *  * \n  5   129.250.3.94  8.637ms  8.498ms  8.451ms \n  6   128.241.8.175  9.279ms  9.260ms  9.326ms \n  7   131.125.155.83  9.178ms  8.917ms  9.105ms \n  8   *  *  * \n  9   *  *  * \n 10   *  *  * \n 11   *  *  * \n 12   *  *  * \n 13   *  *  * \n 14   *  *  * \n 15   *  *  * \n"
}