{
  "timestamp": "2025-09-27T03:27:09.707033-03:00",
  "url": "https://www.godo.sr/nl/wisselkoersnoteringen/",
  "method": "GET",
  "headers": {
    "user-agent": "Mozilla/5.0 (Windows NT 10.0; Win64; x64) AppleWebKit/537.36 (KHTML, like Gecko) Chrome/124.0.0.0 Safari/537.36",
    "accept": "*/*",
    "accept-language": "nl-NL,nl;q=0.9,en;q=0.8",
    "connection": "keep-alive"
  },
  "body": "None",
  "ip_local": "127.0.1.1",
  "traceroute": "traceroute to uwxiy.x.incapdns.net (199.83.129.128), 15 hops max\n  1   140.204.226.223  0.315ms  0.215ms  0.133ms \n  2   209.120.142.218  1.212ms  1.103ms  1.070ms \n  3   209.120.142.217  1.743ms  2.277ms  2.315ms \n  4   141.136.111.138  39.307ms  40.200ms  39.613ms \n  5   72.29.211.246  38.811ms  38.919ms  39.038ms \n  6   *  *  * \n  7   *  *  * \n  8   *  *  * \n  9   *  *  * \n 10   *  *  * \n 11   *  *  * \n 12   *  *  * \n 13   *  *  * \n 14   *  *  * \n 15   *  *  * \n"
}