{
  "timestamp": "2025-12-30T21:06:59.132235-03:00",
  "url": "https://www.godo.sr/nl/wisselkoersnoteringen/",
  "method": "GET",
  "headers": {
    "user-agent": "Mozilla/5.0 (Windows NT 10.0; Win64; x64) AppleWebKit/537.36 (KHTML, like Gecko) Chrome/124.0.0.0 Safari/537.36",
    "accept": "*/*",
    "accept-language": "nl-NL,nl;q=0.9,en;q=0.8",
    "connection": "keep-alive"
  },
  "body": "None",
  "ip_local": "127.0.1.1",
  "traceroute": "traceroute to www.godo.sr.cdn.cloudflare.net (172.66.154.95), 15 hops max\n  1   157.137.146.56  0.210ms  0.139ms  0.120ms \n  2   140.204.28.36  15.672ms  11.693ms  11.492ms \n  3   140.204.28.37  10.558ms  10.502ms  11.668ms \n  4   141.101.72.83  18.064ms  12.214ms  11.956ms \n  5   172.66.154.95  8.992ms  8.884ms  8.890ms \n"
}