{
  "timestamp": "2025-12-17T06:09:13.624078-03:00",
  "url": "https://vcbbank.sr/",
  "method": "GET",
  "headers": {
    "User-Agent": "Mozilla/5.0",
    "Accept-Encoding": "gzip, deflate",
    "Accept": "*/*",
    "Connection": "keep-alive"
  },
  "body": "None",
  "ip_local": "127.0.1.1",
  "traceroute": "traceroute to vcbbank.sr (199.223.114.132), 15 hops max\n  1   157.137.147.206  0.268ms  0.104ms  0.183ms \n  2   4.7.247.122  3.845ms  1.257ms  1.132ms \n  3   *  *  * \n  4   4.69.219.110  70.666ms  76.285ms  63.281ms \n  5   198.46.80.117  57.080ms  57.012ms  57.060ms \n  6   198.46.80.117  57.136ms  57.099ms  57.132ms \n  7   198.46.80.15  57.267ms  57.274ms  * \n  8   104.193.140.61  57.266ms  57.249ms  57.235ms \n  9   *  *  * \n 10   *  *  * \n 11   *  *  * \n 12   *  *  * \n 13   *  *  * \n 14   *  *  * \n 15   *  *  * \n"
}