{
  "timestamp": "2025-09-26T17:57:16.079661-03:00",
  "url": "https://www.godo.sr/nl/wisselkoersnoteringen/",
  "method": "GET",
  "headers": {
    "user-agent": "Mozilla/5.0 (Windows NT 10.0; Win64; x64) AppleWebKit/537.36 (KHTML, like Gecko) Chrome/124.0.0.0 Safari/537.36",
    "accept": "*/*",
    "accept-language": "nl-NL,nl;q=0.9,en;q=0.8",
    "connection": "keep-alive"
  },
  "body": "None",
  "ip_local": "127.0.1.1",
  "traceroute": "traceroute to uwxiy.x.incapdns.net (199.83.129.128), 15 hops max\n  1   140.204.227.61  0.251ms  0.136ms  0.112ms \n  2   128.241.6.197  0.510ms  0.435ms  0.453ms \n  3   128.241.6.196  28.531ms  32.041ms  34.138ms \n  4   *  *  * \n  5   *  *  * \n  6   129.250.4.7  43.806ms  43.643ms  43.614ms \n  7   128.241.13.18  43.690ms  43.784ms  43.978ms \n  8   *  *  * \n  9   *  *  * \n 10   *  *  * \n 11   *  *  * \n 12   *  *  * \n 13   *  *  * \n 14   *  *  * \n 15   *  *  * \n"
}